[
    {
        "url": "https://www.salonsaffier.nl/",
        "title": "Salon Saffier is de uitgever van De Utrechtse Boekhouder, tijdschrift gewijd aan Utrechts literair erfgoed.",
        "text": "Salon Saffier"
    },
    {
        "url": "https://www.avondlog.nl/",
        "title": "Het dagelijkse weblog van Wim Noordhoek",
        "text": "Avondlog"
    },
    {
        "url": "https://erfgoedcentrumzutphen.nl/",
        "title": "Alles over Zutphens stadsdichters",
        "text": "Dichter bij Zutphen"
    },
    {
        "url": "https://www.kopwitzutphen.nl/",
        "title": "Literaire activiteiten in Zutphen",
        "text": "Kopwit Zutphen"
    },
    {
        "url": "https://zutphenliterair.nl/ida-gerhardt-poezieprijs/",
        "title": "Tweejaarlijkse prijs van de gemeente Zutphen",
        "text": "Ida Gerhardt Poëzieprijs"
    },
    {
        "url": "https://librije-zutphen.nl/",
        "title": "Unieke middeleeuwse kettingbibliotheek",
        "text": "Librije"
    },
    {
        "url": "https://somerentenbosch.nl/",
        "title": "De literaire boekhandel van Zutphen, sinds 1844",
        "text": "Van Someren &amp; Ten Bosch"
    }
]